module_goes_here/__init__.py
module_goes_here/__main__.py
module_goes_here/version.py
module_goes_here-0.1.0.dist-info/LICENSE
module_goes_here-0.1.0.dist-info/METADATA
module_goes_here-0.1.0.dist-info/WHEEL
module_goes_here-0.1.0.dist-info/top_level.txt
module_goes_here-0.1.0.dist-info/RECORD
